pyxdia/__init__.py
pyxdia/__main__.py
pyxdia/__version__.py
pyxdia/pdb.py
pyxdia/bin/msdia140.dll
pyxdia/bin/xdia.LICENSE.txt
pyxdia/bin/xdia.exe
pyxdia/bin/xdialdr
pyxdia/bin/xdialdr.LICENSE.txt
pyxdia-0.1.0.dist-info/METADATA
pyxdia-0.1.0.dist-info/WHEEL
pyxdia-0.1.0.dist-info/top_level.txt
pyxdia-0.1.0.dist-info/RECORD
pyxdia-0.1.0.dist-info/licenses/LICENSE.txt
