Metadata-Version: 2.4
Name: pyxdia
Version: 0.1.0
Summary: Extract useful program information from PDB files
License: Copyright 2024 Matt Borgerson
Project-URL: Homepage, https://github.com/mborgerson/xdia
Classifier: Programming Language :: Python
Classifier: Programming Language :: Python :: 3
Classifier: Programming Language :: Python :: 3 :: Only
Classifier: Programming Language :: Python :: 3.10
Classifier: Programming Language :: Python :: 3.11
Classifier: Programming Language :: Python :: 3.12
Classifier: Programming Language :: Python :: 3.13
Requires-Python: >=3.10
License-File: LICENSE.txt
Dynamic: license-file
